setup.py
pycdek/__init__.py
pycdek/client.py
pycdek.egg-info/PKG-INFO
pycdek.egg-info/SOURCES.txt
pycdek.egg-info/dependency_links.txt
pycdek.egg-info/top_level.txt