Metadata-Version: 1.1
Name: pycdek
Version: 0.3.1
Summary: Client for CDEK API
Home-page: http://github.com/onrik/pycdek/
Author: Andrey
Author-email: and@rey.im
License: MIT
Download-URL: https://github.com/onrik/pycdek/tarball/master
Platform: UNKNOWN
Classifier: Development Status :: 4 - Beta
Classifier: Environment :: Web Environment
Classifier: Intended Audience :: Developers
Classifier: License :: OSI Approved :: MIT License
Classifier: Operating System :: OS Independent
Classifier: Programming Language :: Python
Classifier: Programming Language :: Python :: 2
Classifier: Topic :: Software Development :: Libraries :: Python Modules
